pywrench/__init__.py
pywrench-0.0.1.dist-info/WHEEL
pywrench-0.0.1.dist-info/METADATA
pywrench-0.0.1.dist-info/RECORD
