Metadata-Version: 2.1
Name: pywrench
Version: 0.0.1
Summary: Pluggable configuration system
License: MIT
Author: Robert Wikman
Author-email: rbw@vault13.org
Requires-Python: >=3.6,<4.0
Classifier: License :: OSI Approved :: MIT License
Classifier: Programming Language :: Python :: 3
Classifier: Programming Language :: Python :: 3.6
Classifier: Programming Language :: Python :: 3.7
